<annotation>
	<folder>A38 images</folder>
	<filename>frame1569.jpg</filename>
	<path>C:\Users\Vishwanath Varma\Documents\images\A38 images\frame1569.jpg</path>
	<source>
		<database>Unknown</database>
	</source>
	<size>
		<width>1920</width>
		<height>1080</height>
		<depth>3</depth>
	</size>
	<segmented>0</segmented>
	<object>
		<name>fish</name>
		<pose>Unspecified</pose>
		<truncated>0</truncated>
		<difficult>0</difficult>
		<bndbox>
			<xmin>326</xmin>
			<ymin>798</ymin>
			<xmax>511</xmax>
			<ymax>935</ymax>
		</bndbox>
	</object>
	<object>
		<name>fish</name>
		<pose>Unspecified</pose>
		<truncated>0</truncated>
		<difficult>0</difficult>
		<bndbox>
			<xmin>216</xmin>
			<ymin>257</ymin>
			<xmax>289</xmax>
			<ymax>494</ymax>
		</bndbox>
	</object>
</annotation>
